{"ballerinax/googleapis.calendar:0.1.3:CalendarResource":[{"kind":"calendar#calendar", "etag":"\"Y4KkcV6Cyg8J5vF9reAuo9s954Y\"", "id":"319d173rg5asq31snl30q0djg0@group.calendar.google.com", "summary":"MyPersonalCalendar", "timeZone":"UTC", "conferenceProperties":{"allowedConferenceSolutionTypes":["hangoutsMeet"]}},{"kind":"calendar#calendar", "etag":"\"ts-TlWTSV7Hzgb2k4Gs6rbuhj9s\"", "id":"98kr90pnl0s2ut21lg9ja3j5to@group.calendar.google.com", "summary":"MyOfficeCalendar", "timeZone":"UTC", "conferenceProperties":{"allowedConferenceSolutionTypes":["hangoutsMeet"]}},{"kind":"calendar#calendar", "etag":"\"VDvoMEPYkXKiJR0cWBJ283cPxGA\"", "id":"apcb3c0ppa7m9ijj9vrkgq7t10@group.calendar.google.com", "summary":"MyToDoListCalendar", "timeZone":"UTC", "conferenceProperties":{"allowedConferenceSolutionTypes":["hangoutsMeet"]}}]}